{
    "privateAssets": {
        "1668047859902729:94127": {
            "isLazyAsset": false,
            "uid": "1668047859902729:94127",
            "type": "Asset.MLAsset",
            "name": "Embedder.onnx",
            "provider": {
                "type": "Provider.BinFileProvider",
                "filename": "Files/File_1682017631896815_495.dnn",
                "fileinfo": {
                    "path": "Files/File_1682017631896815_495.dnn",
                    "location": 0
                }
            },
            "inputs": [
                {
                    "input": {
                        "name": "rays",
                        "shape": [
                            24.0,
                            10000.0,
                            1.0
                        ],
                        "texture": "-1:-1",
                        "transformer0": {
                            "uid": "1691728294050135:1901",
                            "type": "Transformer",
                            "FlipX": false,
                            "FlipY": false,
                            "useStretch": true,
                            "AlignFillColor": [
                                0.0,
                                0.0,
                                0.0,
                                1.0
                            ],
                            "RotationMode": {
                                "value": 0,
                                "description": "none"
                            },
                            "VertAlignment": {
                                "value": 1,
                                "description": "Center"
                            },
                            "HoriAlignment": {
                                "value": 1,
                                "description": "Center"
                            },
                            "ResamplingQ": {
                                "value": 0,
                                "description": "none"
                            }
                        }
                    }
                }
            ],
            "outputs": [
                {
                    "output": {
                        "name": "embbrays",
                        "shape": [
                            24.0,
                            10000.0,
                            13.0
                        ],
                        "texture": "-1:-1",
                        "transformer0": "-1:-1",
                        "outputMode": 0
                    }
                }
            ]
        }
    }
}
