{
    "1682017631896758:421": {
        "IResourceController": {
            "name": "Diff",
            "type": 1,
            "subtype": 9,
            "dependency": 1,
            "hidden": false,
            "uid": "1588296316843646:534374",
            "fileId": "1682017631896762:461",
            "originalId": "1682017631896770:462",
            "expected_hash": "0febd5bc9be04ba2e49753f22e5c565d"
        },
        "IResourceManager": {
            "uid": "1588296316843646:534374",
            "name": "Files/File_1682017631896762_461.jpeg",
            "flags": 1
        }
    },
    "1682017631896762:461": {
        "IFileManager": {
            "path": "Files/File_1682017631896762_461.jpeg"
        }
    },
    "1682017631896770:462": {
        "IFileManager": {
            "path": "Files/File_1682017631896770_462.jpeg"
        }
    }
}
